t2string/__init__.py
t2string/t2string.py
t2string-0.1.5.dist-info/METADATA
t2string-0.1.5.dist-info/WHEEL
t2string-0.1.5.dist-info/top_level.txt
t2string-0.1.5.dist-info/RECORD
