Metadata-Version: 2.4
Name: t2string
Version: 0.1.5
Summary: Converts new template string (t-string)(in python 3.14) to normal string
Author-email: Yuvneil <yuvneiledu44@gmail.com>
License: MIT
Project-URL: Homepage, https://github.com/yourusername/mypackage
Requires-Python: >=3.14
